{
  "id": "hero-main",
  "name": "Hero Section",
  "type": "container",
  "category": "content",
  "description": "Main hero section with headline, description, and CTA",
  "properties": {
    "badgeText": {
      "type": "string",
      "description": "Top badge text",
      "editable": true,
      "default": "Trusted by great teams"
    },
    "showBadge": {
      "type": "boolean",
      "description": "Show/hide badge",
      "editable": true,
      "default": true
    },
    "headingLine1": {
      "type": "string",
      "description": "First line of heading",
      "editable": true,
      "required": true,
      "default": "Grow your business"
    },
    "headingLine2": {
      "type": "string",
      "description": "Second line of heading (highlighted)",
      "editable": true,
      "required": true,
      "default": "with a simple hero"
    },
    "description": {
      "type": "string",
      "description": "Hero description text",
      "editable": true,
      "required": true,
      "default": "Use this space for a short, neutral description of your product or service."
    },
    "ctaButtonText": {
      "type": "string",
      "description": "CTA button text",
      "editable": true,
      "default": "Get Started"
    },
    "showClientLogos": {
      "type": "boolean",
      "description": "Show client logos carousel",
      "editable": true,
      "default": true
    },
    "clientLogos": {
      "type": "array",
      "description": "Client logos for the carousel",
      "editable": true,
      "default": [
        { "src": "/placeholder.svg", "alt": "Client Logo 1" },
        { "src": "/placeholder.svg", "alt": "Client Logo 2" },
        { "src": "/placeholder.svg", "alt": "Client Logo 3" },
        { "src": "/placeholder.svg", "alt": "Client Logo 4" },
        { "src": "/placeholder.svg", "alt": "Client Logo 5" },
        { "src": "/placeholder.svg", "alt": "Client Logo 6" },
        { "src": "/placeholder.svg", "alt": "Client Logo 7" },
        { "src": "/placeholder.svg", "alt": "Client Logo 8" }
      ]
    },
    "backgroundType": {
      "type": "string",
      "description": "Type of background (color, image, or gradient)",
      "editable": true,
      "default": "gradient"
    },
    "backgroundColor": {
      "type": "string",
      "description": "Background color",
      "editable": true,
      "default": "#ffffff"
    }
  },
  "editor": "ContainerEditor",
  "version": "1.0.0",
  "tenant_scope": "tenant",
  "tags": ["hero", "banner", "cta", "homepage"],
  "dependencies": ["framer-motion", "lucide-react"],
  "last_updated": "2025-10-17T12:00:00Z"
}